f7/__main__.py
f7/api.py
f7/assets/icon.png
f7/assets/note.txt
f7/clip.py
f7/converters.py
f7/core.py
f7/custom_types.py
f7/hotkey.py
f7/plugins/__init__.py
f7/plugins/ai_ollama_plugin.py
f7/plugins/base_plugin.py
f7/plugins/cmd_plugin.py
f7/plugins/python_eval_plugin/__init__.py
f7/plugins/python_eval_plugin/cyber.py
f7/plugins/python_eval_plugin/python_eval_plugin.py
f7/plugins/python_eval_plugin/python_utils.py
f7/plugins/python_eval_plugin/static_globals.py
f7/register_os.py
f7/settings.py
f7/settingsUI.py
f7/singleInstance.py
f7/ui.py
f7/utils.py
f7/window.py
f7/workaround.py
f7-0.1.3.dist-info/LICENSE
f7-0.1.3.dist-info/METADATA
f7-0.1.3.dist-info/WHEEL
f7-0.1.3.dist-info/entry_points.txt
f7-0.1.3.dist-info/RECORD
