Metadata-Version: 2.3
Name: f7
Version: 0.1.3
Summary: F7 is a productivity tool to manipulate strings using python,shell or AI
License: MIT
Keywords: automation,qt,gui,productivity,command,ollama
Author: matan h
Requires-Python: >=3.9
Classifier: Programming Language :: Python :: 3
Classifier: License :: OSI Approved :: MIT License
Classifier: Operating System :: OS Independent
Requires-Dist: appdirs (>=1.4.4,<2.0.0)
Requires-Dist: llama-cpp-python (>=0.3.9,<0.4.0)
Requires-Dist: ollama (>=0.4.8,<0.5.0)
Requires-Dist: pyautogui (>=0.9.54,<0.10.0)
Requires-Dist: pynput (>=1.8.1,<2.0.0) ; sys_platform == "win32"
Requires-Dist: pyperclip (>=1.9.0,<2.0.0)
Requires-Dist: pyqt6 (>=6.9.0,<7.0.0)
Requires-Dist: python-string-utils (>=1.0.0,<2.0.0)
Requires-Dist: qt-material (>=2.17,<3.0)
Requires-Dist: tomli (>=2.2.1,<3.0.0)
Requires-Dist: tomli-w (>=1.2.0,<2.0.0)
Project-URL: Homepage, https://github.com/matan-h/f7
Project-URL: Repository, https://github.com/matan-h/f7
